dify_oapi/__init__.py
dify_oapi/api/__init__.py
dify_oapi/api/chat/__init__.py
dify_oapi/api/chat/service.py
dify_oapi/api/chat/v1/__init__.py
dify_oapi/api/chat/v1/model/__init__.py
dify_oapi/api/chat/v1/model/audio_to_text_request.py
dify_oapi/api/chat/v1/model/audio_to_text_request_body.py
dify_oapi/api/chat/v1/model/audio_to_text_response.py
dify_oapi/api/chat/v1/model/chat_request.py
dify_oapi/api/chat/v1/model/chat_request_body.py
dify_oapi/api/chat/v1/model/chat_request_file.py
dify_oapi/api/chat/v1/model/chat_response.py
dify_oapi/api/chat/v1/model/delete_conversation_request.py
dify_oapi/api/chat/v1/model/delete_conversation_request_body.py
dify_oapi/api/chat/v1/model/delete_conversation_response.py
dify_oapi/api/chat/v1/model/get_conversation_list_request.py
dify_oapi/api/chat/v1/model/get_conversation_list_response.py
dify_oapi/api/chat/v1/model/message_history_request.py
dify_oapi/api/chat/v1/model/message_history_response.py
dify_oapi/api/chat/v1/model/message_suggested_request.py
dify_oapi/api/chat/v1/model/message_suggested_response.py
dify_oapi/api/chat/v1/model/rename_conversation_request.py
dify_oapi/api/chat/v1/model/rename_conversation_request_body.py
dify_oapi/api/chat/v1/model/rename_conversation_response.py
dify_oapi/api/chat/v1/model/stop_chat_request.py
dify_oapi/api/chat/v1/model/stop_chat_request_body.py
dify_oapi/api/chat/v1/model/stop_chat_response.py
dify_oapi/api/chat/v1/resource/__init__.py
dify_oapi/api/chat/v1/resource/audio.py
dify_oapi/api/chat/v1/resource/chat.py
dify_oapi/api/chat/v1/resource/conversation.py
dify_oapi/api/chat/v1/resource/message.py
dify_oapi/api/chat/v1/version.py
dify_oapi/api/completion/__init__.py
dify_oapi/api/completion/service.py
dify_oapi/api/completion/v1/__init__.py
dify_oapi/api/completion/v1/model/__init__.py
dify_oapi/api/completion/v1/model/completion_request.py
dify_oapi/api/completion/v1/model/completion_request_body.py
dify_oapi/api/completion/v1/model/completion_request_body_input.py
dify_oapi-0.0.15.dist-info/LICENSE
dify_oapi-0.0.15.dist-info/METADATA
dify_oapi-0.0.15.dist-info/WHEEL
dify_oapi-0.0.15.dist-info/RECORD
