Metadata-Version: 2.1
Name: dify-oapi
Version: 0.0.15
Summary: A package for interacting with the Dify Service-API
Home-page: https://github.com/QiMington/dify-oapi
License: MIT
Keywords: dify,nlp,ai,language-processing
Author: QiMington
Author-email: qimington@gmail.com
Requires-Python: >=3.10,<4.0
Classifier: License :: OSI Approved :: MIT License
Classifier: Programming Language :: Python :: 3
Classifier: Programming Language :: Python :: 3.10
Classifier: Programming Language :: Python :: 3.11
Classifier: Programming Language :: Python :: 3.12
Classifier: Programming Language :: Python :: 3.13
Requires-Dist: backoff (>=2.2.1,<3.0.0)
Requires-Dist: httpx (>=0.24,<1.0)
Requires-Dist: pydantic (>=1.10,<3.0.0)
Requires-Dist: typing-extensions (>=4.15.0,<5.0.0)
Project-URL: Source, https://github.com/QiMington/dify-oapi
